LICENSE
MANIFEST.in
README.md
pyproject.toml
setup.cfg
setup.py
src/diffusers/__init__.py
src/diffusers/configuration_utils.py
src/diffusers/dependency_versions_check.py
src/diffusers/dependency_versions_table.py
src/diffusers/image_processor.py
src/diffusers/loaders.py
src/diffusers/optimization.py
src/diffusers/pipeline_utils.py
src/diffusers/training_utils.py
src/diffusers/commands/__init__.py
src/diffusers/commands/diffusers_cli.py
src/diffusers/commands/env.py
src/diffusers/experimental/__init__.py
src/diffusers/experimental/rl/__init__.py
src/diffusers/experimental/rl/value_guided_sampling.py
src/diffusers/models/__init__.py
src/diffusers/models/attention.py
src/diffusers/models/attention_flax.py
src/diffusers/models/attention_processor.py
src/diffusers/models/autoencoder_kl.py
src/diffusers/models/controlnet.py
src/diffusers/models/controlnet_flax.py
src/diffusers/models/cross_attention.py
src/diffusers/models/dual_transformer_2d.py
src/diffusers/models/embeddings.py
src/diffusers/models/embeddings_flax.py
src/diffusers/models/modeling_flax_pytorch_utils.py
src/diffusers/models/modeling_flax_utils.py
src/diffusers/models/modeling_pytorch_flax_utils.py
src/diffusers/models/modeling_utils.py
src/diffusers/models/prior_transformer.py
src/diffusers/models/resnet.py
src/diffusers/models/resnet_flax.py
src/diffusers/models/t5_film_transformer.py
src/diffusers/models/transformer_2d.py
src/diffusers/models/transformer_temporal.py
src/diffusers/models/unet_1d.py
src/diffusers/models/unet_1d_blocks.py
src/diffusers/models/unet_2d.py
src/diffusers/models/unet_2d_blocks.py
src/diffusers/models/unet_2d_blocks_flax.py
src/diffusers/models/unet_2d_condition.py
src/diffusers/models/unet_2d_condition_flax.py
src/diffusers/models/unet_3d_blocks.py
src/diffusers/models/unet_3d_condition.py
src/diffusers/models/vae.py
src/diffusers/models/vae_flax.py
src/diffusers/models/vq_model.py
src/diffusers/pipelines/__init__.py
src/diffusers/pipelines/onnx_utils.py
src/diffusersTangkhode.egg-info/PKG-INFO
src/diffusersTangkhode.egg-info/SOURCES.txt
src/diffusersTangkhode.egg-info/dependency_links.txt
src/diffusersTangkhode.egg-info/entry_points.txt
src/diffusersTangkhode.egg-info/requires.txt
src/diffusersTangkhode.egg-info/top_level.txt