Metadata-Version: 2.1
Name: diffusersTangkhode
Version: 0.0.1
Summary: Diffusers
Home-page: https://github.com/caymanwjeffers/diffusersTangkhode
Author: tangkhode
Author-email: caymanwjeffers@gmail.com
License: Apache
Download-URL: https://github.com/caymanwjeffers/diffusersTangkhode/archive/refs/tags/v_01.tar.gz
Keywords: deep learning
Platform: UNKNOWN
Classifier: Development Status :: 5 - Production/Stable
Classifier: Intended Audience :: Developers
Classifier: Intended Audience :: Education
Classifier: Intended Audience :: Science/Research
Classifier: License :: OSI Approved :: Apache Software License
Classifier: Operating System :: OS Independent
Classifier: Programming Language :: Python :: 3
Classifier: Programming Language :: Python :: 3.7
Classifier: Programming Language :: Python :: 3.8
Classifier: Programming Language :: Python :: 3.9
Classifier: Topic :: Scientific/Engineering :: Artificial Intelligence
Requires-Python: >=3.7.0
Provides-Extra: quality
Provides-Extra: docs
Provides-Extra: training
Provides-Extra: test
Provides-Extra: torch
Provides-Extra: flax
Provides-Extra: dev
License-File: LICENSE
